wagtailgridder/__init__.py
wagtailgridder/_version.py
wagtailgridder/blocks.py
wagtailgridder/models.py
wagtailgridder/settings.py
wagtailgridder/wagtail_hooks.py
wagtailgridder/migrations/0001_squashed_0012_auto_20170607_1317.py
wagtailgridder/migrations/0002_auto_20180220_1101.py
wagtailgridder/migrations/0003_alter_griditemtag_tag.py
wagtailgridder/migrations/0004_alter_griditem_buttons.py
wagtailgridder/migrations/__init__.py
wagtailgridder/static/wagtailgridder/css/grid_index_page.css
wagtailgridder/static/wagtailgridder/css/jquery.gridder.min.css
wagtailgridder/static/wagtailgridder/css/jquery.gridder.min.css.map
wagtailgridder/static/wagtailgridder/js/jquery.gridder.min.js
wagtailgridder/static/wagtailgridder/js/jquery.mixitup.min.js
wagtailgridder/templates/base.html
wagtailgridder/templates/wagtailgridder/grid_index_page.html
wagtailgridder/templates/wagtailgridder/grid_item.html
wagtailgridder/templates/wagtailgridder/blocks/button_section.html
wagtailgridder/templates/wagtailgridder/blocks/document_action_item.html
wagtailgridder/templates/wagtailgridder/blocks/placeholder_action_item.html
wagtailgridder/templates/wagtailgridder/blocks/url_action_item.html
wagtailgridder/templates/wagtailgridder/index/__extra_footer_js.html
wagtailgridder/templates/wagtailgridder/index/__extra_head_bottom.html
wagtailgridder/templates/wagtailgridder/index/__hero_section.html
wagtailgridder/templates/wagtailgridder/index/__wg-content-container.html
wagtailgridder-2.0.0.dist-info/licenses/LICENSE
wagtailgridder-2.0.0.dist-info/METADATA
wagtailgridder-2.0.0.dist-info/WHEEL
wagtailgridder-2.0.0.dist-info/top_level.txt
wagtailgridder-2.0.0.dist-info/RECORD
