Metadata-Version: 2.4
Name: wagtailgridder
Version: 2.0.0
Summary: Dynamic, interactive grid layout for the Django CMS Wagtail.
Author-email: Timothy Allen <tallen@wharton.upenn.edu>
License: BSD-3-Clause
Project-URL: Homepage, https://github.com/wharton/wagtailgridder
Project-URL: Repository, https://github.com/wharton/wagtailgridder
Project-URL: Documentation, https://github.com/wharton/wagtailgridder
Keywords: wagtail,cms,gridder,theme,dynamic
Classifier: Development Status :: 5 - Production/Stable
Classifier: Environment :: Web Environment
Classifier: Intended Audience :: Developers
Classifier: License :: OSI Approved :: BSD License
Classifier: Operating System :: OS Independent
Classifier: Programming Language :: Python :: 3
Classifier: Programming Language :: Python :: 3.8
Classifier: Programming Language :: Python :: 3.9
Classifier: Programming Language :: Python :: 3.10
Classifier: Programming Language :: Python :: 3.11
Classifier: Programming Language :: Python :: 3.12
Classifier: Framework :: Django
Classifier: Framework :: Wagtail
Classifier: Framework :: Wagtail :: 4
Classifier: Framework :: Wagtail :: 5
Classifier: Framework :: Wagtail :: 6
Classifier: Topic :: Internet :: WWW/HTTP
Classifier: Topic :: Internet :: WWW/HTTP :: Dynamic Content
Requires-Python: >=3.7
License-File: LICENSE
Requires-Dist: wagtail>=4.1
Requires-Dist: wagtail-modeladmin
Provides-Extra: dev
Requires-Dist: django-coverage-plugin; extra == "dev"
Requires-Dist: ipython; extra == "dev"
Requires-Dist: pytest-django; extra == "dev"
Requires-Dist: pytest-cov; extra == "dev"
Requires-Dist: ruff; extra == "dev"
Dynamic: license-file
